UcoreOsShiyanZhidaoshuHeYuanmaWangzhi2017/README.md
UcoreOsShiyanZhidaoshuHeYuanmaWangzhi2017/__init__.py
UcoreOsShiyanZhidaoshuHeYuanmaWangzhi2017/__main__.py
UcoreOsShiyanZhidaoshuHeYuanmaWangzhi2017/file.epub
UcoreOsShiyanZhidaoshuHeYuanmaWangzhi2017/index.html
UcoreOsShiyanZhidaoshuHeYuanmaWangzhi2017/css/__init__.py
UcoreOsShiyanZhidaoshuHeYuanmaWangzhi2017/css/annotations.css
UcoreOsShiyanZhidaoshuHeYuanmaWangzhi2017/css/main.css
UcoreOsShiyanZhidaoshuHeYuanmaWangzhi2017/css/normalize.css
UcoreOsShiyanZhidaoshuHeYuanmaWangzhi2017/css/popup.css
UcoreOsShiyanZhidaoshuHeYuanmaWangzhi2017/font/__init__.py
UcoreOsShiyanZhidaoshuHeYuanmaWangzhi2017/font/fontello.eot
UcoreOsShiyanZhidaoshuHeYuanmaWangzhi2017/font/fontello.svg
UcoreOsShiyanZhidaoshuHeYuanmaWangzhi2017/font/fontello.ttf
UcoreOsShiyanZhidaoshuHeYuanmaWangzhi2017/font/fontello.woff
UcoreOsShiyanZhidaoshuHeYuanmaWangzhi2017/img/__init__.py
UcoreOsShiyanZhidaoshuHeYuanmaWangzhi2017/img/annotator-glyph-sprite.png
UcoreOsShiyanZhidaoshuHeYuanmaWangzhi2017/img/annotator-icon-sprite.png
UcoreOsShiyanZhidaoshuHeYuanmaWangzhi2017/img/apple-touch-icon.png
UcoreOsShiyanZhidaoshuHeYuanmaWangzhi2017/img/cancelfullscreen.png
UcoreOsShiyanZhidaoshuHeYuanmaWangzhi2017/img/close.png
UcoreOsShiyanZhidaoshuHeYuanmaWangzhi2017/img/fullscreen.png
UcoreOsShiyanZhidaoshuHeYuanmaWangzhi2017/img/loader.gif
UcoreOsShiyanZhidaoshuHeYuanmaWangzhi2017/img/menu-icon.png
UcoreOsShiyanZhidaoshuHeYuanmaWangzhi2017/img/save.png
UcoreOsShiyanZhidaoshuHeYuanmaWangzhi2017/img/saved.png
UcoreOsShiyanZhidaoshuHeYuanmaWangzhi2017/img/settings-s.png
UcoreOsShiyanZhidaoshuHeYuanmaWangzhi2017/img/settings.png
UcoreOsShiyanZhidaoshuHeYuanmaWangzhi2017/img/star.png
UcoreOsShiyanZhidaoshuHeYuanmaWangzhi2017/js/__init__.py
UcoreOsShiyanZhidaoshuHeYuanmaWangzhi2017/js/epub.js
UcoreOsShiyanZhidaoshuHeYuanmaWangzhi2017/js/epub.min.js
UcoreOsShiyanZhidaoshuHeYuanmaWangzhi2017/js/epub.min.map
UcoreOsShiyanZhidaoshuHeYuanmaWangzhi2017/js/hooks.min.js
ucore_os_shiyan_zhidaoshu_he_yuanma_wangzhi_2017-2024.3.4.0.dist-info/METADATA
ucore_os_shiyan_zhidaoshu_he_yuanma_wangzhi_2017-2024.3.4.0.dist-info/WHEEL
ucore_os_shiyan_zhidaoshu_he_yuanma_wangzhi_2017-2024.3.4.0.dist-info/entry_points.txt
ucore_os_shiyan_zhidaoshu_he_yuanma_wangzhi_2017-2024.3.4.0.dist-info/top_level.txt
ucore_os_shiyan_zhidaoshu_he_yuanma_wangzhi_2017-2024.3.4.0.dist-info/RECORD
